CHANGES.txt
COPYRIGHT.txt
LICENSE.txt
README.txt
TODO.txt
bootstrap.py
buildout.cfg
setup.py
src/z3c/__init__.py
src/z3c.rest.egg-info/PKG-INFO
src/z3c.rest.egg-info/SOURCES.txt
src/z3c.rest.egg-info/dependency_links.txt
src/z3c.rest.egg-info/namespace_packages.txt
src/z3c.rest.egg-info/not-zip-safe
src/z3c.rest.egg-info/requires.txt
src/z3c.rest.egg-info/top_level.txt
src/z3c/rest/README.txt
src/z3c/rest/__init__.py
src/z3c/rest/application.zcml
src/z3c/rest/baseerror.pt
src/z3c/rest/client.py
src/z3c/rest/client.txt
src/z3c/rest/configure.zcml
src/z3c/rest/error.pt
src/z3c/rest/error.py
src/z3c/rest/error.txt
src/z3c/rest/interfaces.py
src/z3c/rest/null.py
src/z3c/rest/null.txt
src/z3c/rest/rest.py
src/z3c/rest/rest.txt
src/z3c/rest/testing.py
src/z3c/rest/traverser.py
src/z3c/rest/traverser.txt
src/z3c/rest/twist.py
src/z3c/rest/zserver.py
src/z3c/rest/tests/__init__.py
src/z3c/rest/tests/folder.pt
src/z3c/rest/tests/folder.py
src/z3c/rest/tests/folder.zcml
src/z3c/rest/tests/ftesting.zcml
src/z3c/rest/tests/test.py